searchmind/__init__.py
searchmind/client.py
searchmind/exceptions.py
searchmind/formatter.py
searchmind-0.1.4.dist-info/METADATA
searchmind-0.1.4.dist-info/WHEEL
searchmind-0.1.4.dist-info/licenses/LICENSE
searchmind-0.1.4.dist-info/RECORD
