Metadata-Version: 2.4
Name: searchmind
Version: 0.1.4
Summary: A simple Python client for the Snapzion Search API, packaged as SearchMind.
Project-URL: Homepage, https://github.com/Niansuh/SearchMind
Project-URL: Bug Tracker, https://github.com/Niansuh/SearchMind/issues
Author-email: Niansuh <contact@typegpt.net>
License-File: LICENSE
Classifier: License :: OSI Approved :: MIT License
Classifier: Operating System :: OS Independent
Classifier: Programming Language :: Python :: 3
Requires-Python: >=3.8
Requires-Dist: requests>=2.25.0
